{
  "0000": "李晓风",
  "0001": "王静怡",
  "0002": "赵文博",
  "0003": "陈思琪",
  "0004": "刘子涵",
  "0005": "周天明",
  "0006": "黄雅婷",
  "0007": "吴昊然",
  "0008": "林雪梅",
  "0009": "郑浩宇",
  "0010": "王强",
  "0011": "张晓梅",
  "0012": "陈浩宇",
  "0013": "刘芳",
  "0014": "赵文博",
  "0015": "黄丽娜",
  "0016": "周伟",
  "0017": "李雪",
  "0018": "孙志远",
  "0019": "吴佳琪",
  "0020": "李晓彤",
  "0021": "张伟强",
  "0022": "赵雅琳",
  "0023": "刘建国",
  "0024": "陈思琪",
  "0025": "王志勇",
  "0026": "黄静怡",
  "0027": "周文博",
  "0028": "林雪梅",
  "0029": "杨志强",
  "0030": "李威松",
  "0031": "王丽萍",
  "0032": "赵志远",
  "0033": "张欣悦",
  "0034": "刘建国",
  "0035": "孙晓梅",
  "0036": "吴天宇",
  "0037": "杨静雅",
  "0038": "陈国强",
  "0039": "林梦琪",
  "0040": "李晓彤",
  "0041": "王志远",
  "0042": "陈雅静",
  "0043": "张伟明",
  "0044": "刘欣怡",
  "0045": "黄俊杰",
  "0046": "周梦瑶",
  "0047": "郑凯文",
  "0048": "徐佳慧",
  "0049": "林志强",
  "0050": "王志远",
  "0051": "李思琪",
  "0052": "张文博",
  "0053": "赵晓琳",
  "0054": "周浩然",
  "0055": "陈梦瑶",
  "0056": "黄宇航",
  "0057": "郑佳怡",
  "0058": "孙伟峰",
  "0059": "吴雨彤",
  "0060": "李晓彤",
  "0061": "王建国",
  "0062": "陈雪梅",
  "0063": "张宇航",
  "0064": "刘芳",
  "0065": "赵子豪",
  "0066": "周丽娟",
  "0067": "孙志强",
  "0068": "黄雅琳",
  "0069": "林志远",
  "0070": "李浩然",
  "0071": "张雅婷",
  "0072": "王建国",
  "0073": "刘晓梅",
  "0074": "陈文博",
  "0075": "赵丽娟",
  "0076": "周志刚",
  "0077": "吴雪莲",
  "0078": "郑伟强",
  "0079": "黄静怡",
  "0080": "李晓梅",
  "0081": "王建国",
  "0082": "张丽华",
  "0083": "赵文杰",
  "0084": "刘芳",
  "0085": "陈志刚",
  "0086": "孙佳琪",
  "0087": "周志强",
  "0088": "杨梦瑶",
  "0089": "吴海涛",
  "0090": "张伟强",
  "0091": "李晓彤",
  "0092": "王建国",
  "0093": "陈雅琳",
  "0094": "刘志强",
  "0095": "赵梦瑶",
  "0096": "周立峰",
  "0097": "孙静怡",
  "0098": "黄志刚",
  "0099": "吴敏慧"
}